{"cod_insee": "59117", "cod_dpt": "59", "edition": "DOUAISIS", "commune": "Bugnicourt", "commune_norm": "bugnicourt", "population_2023": 1095, "nb_listes": 1, "statut": "ok", "listes": [{"num_liste": 1, "num_panneau": 1, "nom_liste": "BUGNICOURT UN VILLAGE QUI NOUS RASSEMBLE", "nuance_code": "", "nuance_lib": "", "tete_liste": "M. Michel SALLIO", "nb_candidats": 17, "candidats": ["M. Michel SALLIO", "Mme Magalie PHILIPPE", "M. Thierry USAI", "Mme Emmanuelle CHARLEZ", "M. Daniel DUFOUR", "Mme Gaëlle HAQUETTE", "M. Patrick DUCCESCHI", "Mme Nathalie MICHEL", "M. David MARCHESAN", "Mme Lolita PIROTTE-BLERVACQ", "M. Sebastien DELBART", "Mme Ingrid BRIEUX", "M. Christophe MICHEL", "Mme Tatiana MASCAUX", "M. Frederic LESNE", "Mme Margaret PETIT-RENEL", "M. Maxime MANET"]}]}