{"cod_insee": "59127", "cod_dpt": "59", "edition": "CAMBRESIS", "commune": "Capelle", "commune_norm": "capelle", "population_2023": 135, "nb_listes": 1, "statut": "ok", "listes": [{"num_liste": 1, "num_panneau": 1, "nom_liste": "Cap Avenir", "nuance_code": "", "nuance_lib": "", "tete_liste": "M. Christophe BISIAUX", "nb_candidats": 11, "candidats": ["M. Christophe BISIAUX", "Mme Anne Sophie DECAUDIN", "M. Pascal STIÉVENARD", "Mme Véronique NIGOT", "M. Gérald LAURETTE", "Mme Perrine DELAPORTE-MOUCHOTTE", "M. Franck BRUYANT", "Mme Claire DURANT", "M. Aurélien ZAKROCKI", "Mme Marie-Anne VERCHAIN", "M. Théo BISIAU"]}]}