{"cod_insee": "59212", "cod_dpt": "59", "edition": "HAZEBROUCK ET LA FLANDRE", "commune": "Estaires", "commune_norm": "estaires", "population_2023": 6525, "nb_listes": 3, "statut": "ok", "listes": [{"num_liste": 1, "nom_liste": "Estaires au coeur", "nuance_code": "LDVD", "nuance_lib": "Liste divers droite", "tete_liste": "M. Michaël PARENT", "nb_candidats": 31, "candidats": ["M. Michaël PARENT", "Mme Valérie GRUSON", "M. Jimmy MASSON", "Mme Véronique VANMEENEN", "M. Ryan EVRAERE", "Mme Béatrice TRINELLE", "M. Hugo VERDOIS", "Mme Nathalie CARLIER", "M. Frédéric PALADE", "Mme Véronique LEROY", "M. Christian STAELENS", "Mme Stéphanie PERIER", "M. Jacky GAPINSKI", "Mme Marie VIENNE", "M. Éric BARUZZI", "Mme Amélie PALADE", "M. Ali ADJAOUD", "Mme Angélique PARENT", "M. Fabien GRUHIER", "Mme Emilie MINNEBOIS", "M. Grégoire PARENT", "Mme Gladys VANACKER", "M. Damien GRUSON", "Mme Florence LOTTERIE", "M. Xavier GRUSON", "Mme Brigitte HAVEZ", "M. Francis SLUM", "Mme Noémie CHOQUEL", "M. Philippe GRUHIER", "Mme Nicole DUTHOIT", "M. Alain BARDOUIL"]}, {"num_liste": 2, "nom_liste": "EAV", "nuance_code": "LDVC", "nuance_lib": "Liste divers centre", "tete_liste": "Mme Dorothée BERTRAND", "nb_candidats": 31, "candidats": ["Mme Dorothée BERTRAND", "M. Yves COLPAERT", "Mme Augustine VILLE", "M. Frédéric DUBUS", "Mme Audrey BÉAGUE", "M. François-Xavier HENNEON", "Mme Francine MOURIKS", "M. Gérard BELLENGIER", "Mme Meghann WILLEMS", "M. Yann NORMAND", "Mme Monique DUHAYON", "M. Robin QUEVILLART", "Mme Tifenn LIEVIN", "M. Stéphane DESCAMPS", "Mme Brigitte CAMPAGNE", "M. Quentin DELAY", "Mme Julie BORELLE", "M. Jean-Marie HOORNAERT", "Mme Véronique VERGULDEZOONE", "M. Bruno DASSONVILLE", "Mme Bérangère MAHAUDEN VILLE", "M. Jean-Michel BLAIN", "Mme Amélie BEAUSSART", "M. Eric DEWULF", "Mme Louise LARTISIEN", "M. Rodrigue SAWRAS", "Mme Johanne HAVET", "M. Philippe DELMOTTE", "Mme Violette DESCAMPS", "M. Frédéric POISSONNIER", "Mme Marie-Christine DEHAENE"]}, {"num_liste": 3, "nom_liste": "EVVVV", "nuance_code": "LDVC", "nuance_lib": "Liste divers centre", "tete_liste": "M. Sébastien GISQUIERE", "nb_candidats": 31, "candidats": ["M. Sébastien GISQUIERE", "Mme Pascale ALGOËT", "M. Romain BUISINE", "Mme Laëtitia LEGRAND", "M. Jérôme BRABANT", "Mme Justine VAN-LANDUYT", "M. Grégory MILLE", "Mme Céline DEBRAY", "M. Jean-Jacques ROBAERT", "Mme Louise SAINTENOY CAMPAGNE", "M. Jean-Yves GROSSARD", "Mme Valérie DOUCHE", "M. Franck DEROO", "Mme Amandine BERTAUX", "M. Florian MERIAUX", "Mme Emilie CHAVATTE", "M. Bruno DESCAMD", "Mme Magali DRIZA", "M. Sylvain WEEKS", "Mme Emilie GOETHALS", "M. Enzo CARPENTIER", "Mme Emilie DUBRULLE", "M. Dominique VIALLETON", "Mme Claire AHACHE", "M. Geoffray MOUCHON", "Mme Nathalie BLONDEZ", "M. Laurent BROLL", "Mme Nathalie DEBACKER", "M. Hugo GISQUIERE", "Mme Laurie DESCAMD", "M. Jean-François MIENNEE"]}]}