{"cod_insee": "59265", "cod_dpt": "59", "edition": "SAMBRE-AVESNOIS", "commune": "Gommegnies", "commune_norm": "gommegnies", "population_2023": 2264, "nb_listes": 2, "statut": "ok", "listes": [{"num_liste": 1, "nom_liste": "GOMMEGNIES, CARNOY : AUTREMENT !", "nuance_code": "", "nuance_lib": "", "tete_liste": "M. Olivier LIMELETTE", "nb_candidats": 19, "candidats": ["M. Olivier LIMELETTE", "Mme Isabelle DORGE", "M. Sebastien LOUVRIER", "Mme Magali GILBERT", "M. Cyril MOUILLAT", "Mme Emeline DUPONT", "M. Giuseppe MONTAGNA", "Mme Pauline MELCHIORRE-PETERS", "M. Ludovic ARNAUD", "Mme Anne MERVEAU", "M. Fabrice LELEU", "Mme Marion GOBLET", "M. Philippe DUPONT", "Mme Marine BUGHIN", "M. Mathieu BRIENNE", "Mme Helene SERVAIS-LOMBARDI", "M. Gregory MATHIEU", "Mme Noemi DEVALLEZ", "M. Remy MASSON"]}, {"num_liste": 2, "nom_liste": "Continuons ensemble pour Gommegnies Carnoy !", "nuance_code": "", "nuance_lib": "", "tete_liste": "M. Benoît GUIOST", "nb_candidats": 21, "candidats": ["M. Benoît GUIOST", "Mme Carine FREHAUT", "M. Yvon BRUNELLE", "Mme Chantal PISSON", "M. Maxime HONORE", "Mme Christiane VITO", "M. Thierry SALOMEZ", "Mme Elisabeth CARPENTIER", "M. David LOCQUENEUX", "Mme Anne HENRY", "M. Sébastien DUBRAY", "Mme Pâquerette POLLET", "M. Emmanuel FRUCHART", "Mme Hélène MEIMARAKIS", "M. Arnaud RASSCKAERT", "Mme Juliette DESLAVIERES", "M. Patrice BAILLEUL", "Mme Aline FACON", "M. Clément PETITPREZ", "Mme Marjorie VALIN", "M. James PIRET"]}]}