{"cod_insee": "59271", "cod_dpt": "59", "edition": "DUNKERQUOIS", "commune": "Grande-Synthe", "commune_norm": "grande synthe", "population_2023": 20239, "nb_listes": 2, "statut": "ok", "listes": [{"num_liste": 1, "nom_liste": "REPEALGS", "nuance_code": "LDVG", "nuance_lib": "Liste divers gauche", "tete_liste": "M. Arnaud DECLUNDER", "nb_candidats": 37, "candidats": ["M. Arnaud DECLUNDER", "Mme Sonia BEN MANSOUR", "M. Jérémy BECK", "Mme Marjorie ACS", "M. Karim HAMADI", "Mme Sandra ALGOËT", "M. Patrick HALLIEZ", "Mme Emilie GERARD", "M. Jérôme BERTHE", "Mme Lucie LEUCHART", "M. Habib EL ABBASSI", "Mme Fatima SEGHIR", "M. Julien VANLICHTERVELDE", "Mme Corinne ELIOT", "M. Nicolas CALONNE", "Mme Yasmina LIEGEARD", "M. Smaïn EL KHALOUI", "Mme Angela RITO", "M. Olivier LOUIS", "Mme Hizia HAYAT", "M. René DE-LYS", "Mme Caroline SZWAB", "M. Abdelhakim BADDOU", "Mme Patricia LIMOUSIN", "M. Grégory SCHOEMACKER", "Mme Mathilde PHILIPPE", "M. Warren CORSIEZ", "Mme Sylvie GALLET", "M. Sahin ALTINISIK", "Mme Patricia POULLAIN", "M. Frédéric LEDOUX", "Mme Valérie MARIEL", "M. Jonathan LIAGRE", "Mme Orlanne CUVILLON", "M. Marc KORYTKOWSKI", "Mme Valérie GENU", "M. Mathéo BECK"]}, {"num_liste": 2, "nom_liste": "GSP", "nuance_code": "LUG", "nuance_lib": "Liste d'union à gauche", "tete_liste": "M. Martial BEYAERT", "nb_candidats": 37, "candidats": ["M. Martial BEYAERT", "Mme Nathalie DESMAZIERES", "M. Benoît CUVILLIER", "Mme Anne-Sophie VANELLE", "M. José DA SILVA", "Mme Karima TOUIL AYADA", "M. Nicolas DAMIE", "Mme Karine FAMCHON", "M. Allal AL BOURKI", "Mme Nadia ZEMBILGOTIAN-SARASSIN", "M. Patrick JUSTE", "Mme Michèle HATTAB", "M. Albert DA COSTA CAMPOS CERCA", "Mme Nadia LAMDA", "M. Jamal KHAY", "Mme Keltoum AMICHI", "M. Steven HARDY", "Mme Samira DAOUDI", "M. Krim ROULA", "Mme Véronique PAQUE", "M. Denis VERGRIETE", "Mme Armelle MARESCAUX", "M. Sébastien MARCQ", "Mme Aïcha HABCHI", "M. Pierre MAVAMBU", "Mme Zaina LEMOINE", "M. Kévin DUBAR", "Mme Justine VLIEGHE", "M. Christian MATUSZEWSKI", "Mme Elodie LAMIRAND-MER", "M. Christian BARTHOLOMEUS", "Mme Réjane DAMMAN", "M. Luc DANCEL", "Mme Lamia MOKRANE", "M. Jean PEUPLE", "Mme Nadine DEFLESSELLES", "M. Jean-Pierre DECLERCQ"]}]}