{"cod_insee": "59321", "cod_dpt": "59", "edition": "CAMBRESIS", "commune": "Inchy", "commune_norm": "inchy", "population_2023": 619, "nb_listes": 2, "statut": "ok", "listes": [{"num_liste": 1, "nom_liste": "UNIS POUR INCHY", "nuance_code": "", "nuance_lib": "", "tete_liste": "Mme Delphine RICHEZ", "nb_candidats": 17, "candidats": ["Mme Delphine RICHEZ", "M. Pascal LOCOGE", "Mme Marie-Paule DRUBAY", "M. Richard TABARY", "Mme Marie-Laure VERHAEGHE-THUILLEZ", "M. Lydian BILLIOT", "Mme Lucie VERNEZ", "M. Pierre-Luc LESTOQUOY", "Mme Mathilde DELSART", "M. Rémy DAVOINE", "Mme Christelle DECAILLON-CLOWEZ", "M. Daniel WANECQUE", "Mme Christelle DUCHESNE", "M. Aurélien PECQUEUX", "Mme Marine HAUET-HERBIN", "M. Michel CORDELOIS", "Mme Christelle NOËL"]}, {"num_liste": 2, "nom_liste": "AGIR ENSEMBLE POUR UN NOUVEL ÉLAN", "nuance_code": "", "nuance_lib": "", "tete_liste": "M. Jean-Luc WATREMETZ", "nb_candidats": 15, "candidats": ["M. Jean-Luc WATREMETZ", "Mme Gaëlle GRASSART", "M. Philippe BRELOT", "Mme Caroline CLUNY", "M. Didier CATTIAUX", "Mme Martine LORRIAUX", "M. Pierre KELER", "Mme Catherine DELACROIX", "M. Béranger VILAIN", "Mme Virginie CAUDRELIER", "M. Christophe NOEL", "Mme Cindy DANAPPE", "M. Laurent LAFORCE", "Mme Isabelle BRACQ", "M. David DERACHE"]}]}