{"cod_insee": "59428", "cod_dpt": "59", "edition": "CAMBRESIS", "commune": "Neuville-Saint-Rémy", "commune_norm": "neuville saint remy", "population_2023": 4012, "nb_listes": 3, "statut": "ok", "listes": [{"num_liste": 1, "nom_liste": "NEUVILLE SAINT REMY ENCORE PLUS LOIN", "nuance_code": "LDVD", "nuance_lib": "Liste divers droite", "tete_liste": "M. Christian DUMONT", "nb_candidats": 29, "candidats": ["M. Christian DUMONT", "Mme Julie Denise Odette DURIAU (CODRON)", "M. Jean-Pierre LEGRAND", "Mme Annick CATTEAUX", "M. Grégory DELHALLE", "Mme Martine LABALETTE", "M. Julien TABARIE", "Mme Amandine DEHON", "M. Jean-Marie BARBRY", "Mme Audrey Véronique LACROIX", "M. Guy CARRIÈRE", "Mme Cyrine MEURILLON", "M. Jean-Pierre MORLET", "Mme Catherine COUTELARD", "M. Marc BOVELETTE", "Mme Marie-France VILAIN", "M. Amaury COUPEZ", "Mme Manon LACROIX", "M. Eric Georges PETIT", "Mme Agathe HERBIN", "M. Jean-Marc BOULET", "Mme Amélie TISON", "M. Daniel NOWAK", "Mme Fernande SEGARD", "M. Christophe LANCEL", "Mme Aurélie OBLED", "M. Didier TABARIE", "Mme Anne-Sophie LECLERCQ", "M. Gérard Alain HOQUET"]}, {"num_liste": 2, "nom_liste": "UN NOUVEAU CAP POUR NEUVILLE SAINT REMY", "nuance_code": "LLR", "nuance_lib": "Liste des Républicains", "tete_liste": "M. Vincent FREMEAUX", "nb_candidats": 29, "candidats": ["M. Vincent FREMEAUX", "Mme Nathalie DESSE", "M. Daniel SENE", "Mme Stéphanie DELBART", "M. Victor DUPUIS", "Mme Sabine GAILLARD", "M. Valentin PEREIRA", "Mme Laura BAZIN", "M. Dimitri BORNAND", "Mme Sarah DINAS", "M. Ludovic DHORME", "Mme Sandrine GALLET", "M. David RIGAUT", "Mme Jade LOUISERRE", "M. François REUX", "Mme Sandrine LEFEBVRE", "M. Sébastien DEGROISE", "Mme Isabelle COUVENT", "M. Daniel POIDEVIN", "Mme Sylvie POIDEVIN", "M. Stéphane REMERICQ", "Mme Marieke TIELENS", "M. Sylvain LENGLET", "Mme Marie-Christine CAVRO", "M. Alain VENIAT", "Mme Anne WELTI", "M. Cédric DEVILLERS", "Mme Valérie PILARD", "M. Thierry CAVRO"]}, {"num_liste": 3, "nom_liste": "Ensemble pour Neuville Saint Rémy", "nuance_code": "LDVD", "nuance_lib": "Liste divers droite", "tete_liste": "M. Dimitri ROCQUET", "nb_candidats": 28, "candidats": ["M. Dimitri ROCQUET", "Mme Anaïs VILAIN", "M. Xavier FOSSIER", "Mme Aline GAILLARD", "M. Rémy COLART", "Mme Ingrid BRUNIAUX", "M. Pascal LESAGE", "Mme Marine GILLERON", "M. Tom PAGNIEZ", "Mme Cassandre BRUNIAUX", "M. Andy LAURENS", "Mme Britany HACHE", "M. Bertrand BIGOT", "Mme Marie MORGANO", "M. Bruno PALUMBO", "Mme Pauline DUPLOUYE", "M. Richard MAIRESSE", "Mme Alicia DARTUS", "M. David LEROUX", "Mme Tyffaine GREMAUD", "M. Steve BRU", "Mme Sylvie MORGANO", "M. Thomas SENEZ", "Mme Armelle VIN", "M. Adrien DELACROIX", "Mme Claire CAPLIEZ", "M. Christophe TELLE", "Mme Maria PEREIRA PIRES"]}]}