{"cod_insee": "59517", "cod_dpt": "59", "edition": "CAMBRESIS", "commune": "Les Rues-des-Vignes", "commune_norm": "les rues des vignes", "population_2023": 737, "nb_listes": 1, "statut": "ok", "listes": [{"num_liste": 1, "num_panneau": 1, "nom_liste": "Ensemble pour notre village", "nuance_code": "", "nuance_lib": "", "tete_liste": "M. Fabien CARPENTIER", "nb_candidats": 15, "candidats": ["M. Fabien CARPENTIER", "Mme Marie-Christine DOISY", "M. Dany MERCIER", "Mme Sophie QUEULIN", "M. Jean-Pierre GILLES", "Mme Brigitte VALLEZ", "M. Jean DANEL", "Mme Marie-Anne DURIEUX", "M. Nicolas LEROUGE", "Mme Odile LORIDAN", "M. Damien DUSSART", "Mme Caroline ARDHUIN", "M. Hubert WATREMEZ", "Mme Claudine LANGLAIS", "M. Thierry DENIMAL"]}]}