{"cod_insee": "62090", "cod_dpt": "62", "edition": "ARRAGEOIS-TERNOIS", "commune": "Béalencourt", "commune_norm": "bealencourt", "population_2023": 139, "nb_listes": 1, "statut": "ok", "listes": [{"num_liste": 1, "nom_liste": "Liste d'union communale", "nuance_code": "", "nuance_lib": "", "tete_liste": "M. Benoît THÉRET", "nb_candidats": 11, "candidats": ["M. Benoît THÉRET", "Mme Cathie BAHEU", "M. Frédéric BOLLART", "Mme Christelle GALLET", "M. Olivier BOQUET", "Mme Stéphanie LAGACHE", "M. Quentin FAUQUEMBERGUE", "Mme Malory CARON", "M. Fabien DESTAMPES", "Mme Cécile DELWAULLE", "M. Jeremy DUCROCQ"]}]}