{"cod_insee": "62189", "cod_dpt": "62", "edition": "ARRAGEOIS-TERNOIS", "commune": "Bus", "commune_norm": "bus", "population_2023": 132, "nb_listes": 1, "statut": "ok", "listes": [{"num_liste": 1, "num_panneau": 1, "nom_liste": "ENSEMBLE POUR NOTRE COMMUNE", "nuance_code": "", "nuance_lib": "", "tete_liste": "M. Guy ALEXANDRE", "nb_candidats": 11, "candidats": ["M. Guy ALEXANDRE", "Mme Alexandra LEFEBVRE", "M. Joël BRIDELLE", "Mme Lysiane ALEXANDRE", "M. Joël DUGAVE", "Mme Sarah CABUZEL", "M. Florent POUILLAUDE", "Mme Aurore PAYEN", "M. Nicolas ALEXANDRE", "Mme Gwenaelle BOGAERT", "M. Didier DEULIN"]}]}