{"cod_insee": "62290", "cod_dpt": "62", "edition": "ARRAGEOIS-TERNOIS", "commune": "Ecurie", "commune_norm": "ecurie", "population_2023": 370, "nb_listes": 1, "statut": "ok", "listes": [{"num_liste": 1, "num_panneau": 1, "nom_liste": "ECURIE, UN VILLAGE QUI AVANCE", "nuance_code": "", "nuance_lib": "", "tete_liste": "Mme Charline CAILLIEREZ", "nb_candidats": 11, "candidats": ["Mme Charline CAILLIEREZ", "M. Mikael BACHELET", "Mme Christelle THILLIEZ", "M. Edmond DUFERMONT", "Mme Alexia JOUVENEZ", "M. Daniel ZYWIECKI", "Mme Juliette DHORNE", "M. Lambert GRARE", "Mme Thérèse DELFORGE", "M. Marck MERCIER", "Mme Michèle FOURNIER"]}]}