{"cod_insee": "62365", "cod_dpt": "62", "edition": "ARRAGEOIS-TERNOIS", "commune": "Galametz", "commune_norm": "galametz", "population_2023": 208, "nb_listes": 1, "statut": "ok", "listes": [{"num_liste": 1, "num_panneau": 1, "nom_liste": "Pour les Galamessines et Galamessins", "nuance_code": "", "nuance_lib": "", "tete_liste": "M. Vincent TRAMUSET", "nb_candidats": 13, "candidats": ["M. Vincent TRAMUSET", "Mme Anne DUPONT", "M. Vincent ROUSSEL", "Mme Charlotte BRODEL", "M. Sebastien GREMONT", "Mme Simone BECQUET", "M. Michael TOUPET", "Mme Aurore DUBRULLE", "M. Christophe BERGER", "Mme Monique PREUSS", "M. Hubert LEFEBVRE", "Mme Michele RICHARD", "M. Lionel DEPLANQUE"]}]}