{"cod_insee": "62374", "cod_dpt": "62", "edition": "ARRAGEOIS-TERNOIS", "commune": "Gomiécourt", "commune_norm": "gomiecourt", "population_2023": 151, "nb_listes": 1, "listes": [{"num_liste": 1, "nom_liste": "Unis pour Gomiécourt", "nuance_code": "", "nuance_lib": "", "tete_liste": "M. Hervé COPIN", "nb_candidats": 11, "candidats": ["M. Hervé COPIN", "Mme Priscille PAYEMENT", "M. Jean-Paul BIZART", "Mme Stéphanie MERINO", "M. Thierry TURPIN", "Mme Justine BRACQUART", "M. Mathieu GRAVE", "Mme Sabine LESTOILLE", "M. Renald CORDIER", "Mme Laetitia HENRY", "M. Cédric HENNUYER"]}]}