{"cod_insee": "62760", "cod_dpt": "62", "edition": "AUDOMAROIS", "commune": "Saint-Martin-d'Hardinghem", "commune_norm": "saint martin d hardinghem", "population_2023": 264, "nb_listes": 1, "statut": "ok", "listes": [{"num_liste": 1, "nom_liste": "Bien-vivre à Saint-Martin-d'Hardinghem", "nuance_code": "", "nuance_lib": "", "tete_liste": "Mme Catherine HANQUEZ THION", "nb_candidats": 13, "candidats": ["Mme Catherine HANQUEZ THION", "M. Bernard COURBOIS", "Mme Monique DELATTRE", "M. Pierre-Samuel BAURAIN", "Mme Sylvie FROMENT", "M. Régis DUREY", "Mme Marine BAUVAIS", "M. Bernard SPECQUE", "Mme Manon CLETON", "M. Alexandre FLOURET", "Mme Isabelle MARIETTE", "M. Maxime SCHRYVE", "Mme Marie-Christine VASSEUR"]}]}