{"cod_insee": "62844", "cod_dpt": "62", "edition": "MONTREUILLOIS", "commune": "Verchocq", "commune_norm": "verchocq", "population_2023": 665, "nb_listes": 1, "statut": "ok", "listes": [{"num_liste": 1, "nom_liste": "VERCHOCQ ENSEMBLE", "nuance_code": "", "nuance_lib": "", "tete_liste": "M. Patrick HUGUET", "nb_candidats": 15, "candidats": ["M. Patrick HUGUET", "Mme Isabelle DELAHAYE", "M. Raphaël LALOY", "Mme Aurélie MILON", "M. Yannick LECHERF", "Mme Laurence DUCHATEL", "M. Maxime RANDOUX", "Mme Jenny LECERF", "M. Emeric PICHONNIER", "Mme Audrey FOUACHE", "M. Jordan DANEL", "Mme Virginie BAILLY", "M. Benjamin SOCKEEL", "Mme Céline BERTAUX", "M. Damien CARPENTIER"]}]}