{"cod_insee": "62850", "cod_dpt": "62", "edition": "ARRAGEOIS-TERNOIS", "commune": "Vieil-Hesdin", "commune_norm": "vieil hesdin", "population_2023": 351, "nb_listes": 1, "statut": "ok", "listes": [{"num_liste": 1, "nom_liste": "VIEIL-HESDIN, UN NOUVEL ELAN", "nuance_code": "", "nuance_lib": "", "tete_liste": "M. Christian DRUELLE", "nb_candidats": 13, "candidats": ["M. Christian DRUELLE", "Mme Marie MERLIN", "M. Christian PLANCHON", "Mme Sandrine RUCART", "M. Sébastien LANDRIEUX", "Mme Christelle LEROY", "M. Michael DUTERTRE", "Mme Laëtitia DUVIVIER", "M. Roger VERHAEGHE", "Mme Agnès THERET", "M. Jacques LE GENTIL", "Mme Audrey LEGAREZ", "M. Alain GUILLEMANT"]}]}