{"cod_insee": "62870", "cod_dpt": "62", "edition": "MONTREUILLOIS", "commune": "Wailly-Beaucamp", "commune_norm": "wailly beaucamp", "population_2023": 1062, "nb_listes": 2, "listes": [{"num_liste": 1, "nom_liste": "Unis dans l'action pour Wailly-Beaucamp", "nuance_code": "", "nuance_lib": "", "tete_liste": "M. Alain FRAMERY", "nb_candidats": 17, "candidats": ["M. Alain FRAMERY", "Mme Florine RECOURT", "M. Guillaume LIMOSINO", "Mme Solange RAUSSIN", "M. Thierry LEVELEUX", "Mme Martine HOYEZ", "M. Thierry POIRET", "Mme Sylvie DEBART-DEWINTRE", "M. Régis FONTAINE", "Mme Christelle MOTTE", "M. Marc VASSEUR", "Mme Catherine CARPENTIER", "M. Thomas FONTAINE", "Mme Laura ROUSSEL", "M. Joël NOURRY", "Mme Annick GREMONT", "M. Sébastien RONGER"]}, {"num_liste": 2, "nom_liste": "ACTIVEMENT ! WAILLY-BEAUCAMP", "nuance_code": "", "nuance_lib": "", "tete_liste": "Mme Véronique GRAILLOT", "nb_candidats": 15, "candidats": ["Mme Véronique GRAILLOT", "M. Césaire POCHET", "Mme Christine CARLU", "M. Antoine PROIX", "Mme Aline THERRY", "M. Adrien DUFLOS", "Mme Maud FOURNIER", "M. Jean-Louis SPY", "Mme Sophie BONVOISIN", "M. Julien BEAURAIN", "Mme Agnès BRIOUL", "M. Jean-Luc PONTIE", "Mme Catherine DUPONT", "M. Jacques CRIADO", "Mme Stéphanie MARC"]}]}